RTL/compute/macN.v
//====================================================
// ForgeAI
//
// Module ID : FA-006
// Module    : macN
// Author    : Daniel Simpson
//
// Description:
// Parameterized signed multiply-accumulate unit.
// Performs: acc <= acc + (a * b)
//
// Standards:
// - Positive-edge clock
// - Active-high synchronous reset
// - Active-high enable
// - Active-high accumulator clear
// - Signed arithmetic
//
//====================================================

module macN #(
    parameter DATA_WIDTH = 8,
    parameter ACC_WIDTH  = 32
)(
    input  wire                         clk,
    input  wire                         rst,
    input  wire                         clear_acc,
    input  wire                         en,
    input  wire signed [DATA_WIDTH-1:0] a,
    input  wire signed [DATA_WIDTH-1:0] b,
    output reg  signed [ACC_WIDTH-1:0]  acc
);

    localparam PRODUCT_WIDTH = DATA_WIDTH * 2;

    wire signed [PRODUCT_WIDTH-1:0] product;
    wire signed [ACC_WIDTH-1:0]     product_ext;

    assign product     = a * b;
    assign product_ext = {{(ACC_WIDTH-PRODUCT_WIDTH){product[PRODUCT_WIDTH-1]}}, product};

    always @(posedge clk) begin
        if (rst) begin
            acc <= {ACC_WIDTH{1'b0}};
        end else if (clear_acc) begin
            acc <= {ACC_WIDTH{1'b0}};
        end else if (en) begin
            acc <= acc + product_ext;
        end
    end

endmodule

RTL/compute/processing_element.v
//====================================================
// ForgeAI
//
// Module ID : FA-008
// Module    : processing_element
// Author    : Daniel Simpson
//
// Description:
// AI Processing Element.
// Holds one signed INT8 activation, one signed INT8 weight,
// and feeds them into a signed MAC accumulator.
//
//====================================================

module processing_element (
    input  wire               clk,
    input  wire               rst,

    input  wire               act_load,
    input  wire               wgt_load,
    input  wire               acc_clear,
    input  wire               compute_en,

    input  wire signed [7:0]  act_in,
    input  wire signed [7:0]  wgt_in,

    output wire signed [31:0] acc_out
);

    reg signed [7:0] act_reg;
    reg signed [7:0] wgt_reg;

    always @(posedge clk) begin
        if (rst) begin
            act_reg <= 8'sd0;
            wgt_reg <= 8'sd0;
        end else begin
            if (act_load) begin
                act_reg <= act_in;
            end

            if (wgt_load) begin
                wgt_reg <= wgt_in;
            end
        end
    end

    macN #(
        .DATA_WIDTH(8),
        .ACC_WIDTH(32)
    ) pe_mac (
        .clk(clk),
        .rst(rst),
        .clear_acc(acc_clear),
        .en(compute_en),
        .a(act_reg),
        .b(wgt_reg),
        .acc(acc_out)
    );

endmodule

RTL/compute/compute_tile_4pe.v
//====================================================
// ForgeAI
//
// Module ID : FA-009
// Module    : compute_tile_4pe
// Author    : Daniel Simpson
//
// Description:
// AI compute tile composed of four Processing Elements.
// Accepts packed signed INT8 activations and weights.
// Produces summed INT32 tile result.
//
//====================================================

module compute_tile_4pe (
    input  wire               clk,
    input  wire               rst,

    input  wire               act_load,
    input  wire               wgt_load,
    input  wire               acc_clear,
    input  wire               compute_en,

    input  wire signed [31:0] activations,
    input  wire signed [31:0] weights,

    output wire signed [31:0] tile_result,
    output reg                done
);

    wire signed [31:0] acc0;
    wire signed [31:0] acc1;
    wire signed [31:0] acc2;
    wire signed [31:0] acc3;

    wire signed [7:0] act0 = activations[7:0];
    wire signed [7:0] act1 = activations[15:8];
    wire signed [7:0] act2 = activations[23:16];
    wire signed [7:0] act3 = activations[31:24];

    wire signed [7:0] wgt0 = weights[7:0];
    wire signed [7:0] wgt1 = weights[15:8];
    wire signed [7:0] wgt2 = weights[23:16];
    wire signed [7:0] wgt3 = weights[31:24];

    processing_element pe0 (
        .clk(clk),
        .rst(rst),
        .act_load(act_load),
        .wgt_load(wgt_load),
        .acc_clear(acc_clear),
        .compute_en(compute_en),
        .act_in(act0),
        .wgt_in(wgt0),
        .acc_out(acc0)
    );

    processing_element pe1 (
        .clk(clk),
        .rst(rst),
        .act_load(act_load),
        .wgt_load(wgt_load),
        .acc_clear(acc_clear),
        .compute_en(compute_en),
        .act_in(act1),
        .wgt_in(wgt1),
        .acc_out(acc1)
    );

    processing_element pe2 (
        .clk(clk),
        .rst(rst),
        .act_load(act_load),
        .wgt_load(wgt_load),
        .acc_clear(acc_clear),
        .compute_en(compute_en),
        .act_in(act2),
        .wgt_in(wgt2),
        .acc_out(acc2)
    );

    processing_element pe3 (
        .clk(clk),
        .rst(rst),
        .act_load(act_load),
        .wgt_load(wgt_load),
        .acc_clear(acc_clear),
        .compute_en(compute_en),
        .act_in(act3),
        .wgt_in(wgt3),
        .acc_out(acc3)
    );

    assign tile_result = acc0 + acc1 + acc2 + acc3;

    always @(posedge clk) begin
        if (rst) begin
            done <= 1'b0;
        end else begin
            done <= compute_en;
        end
    end

endmodule

archive/tb_compute_tile_4pe.v
//====================================================
// ForgeAI
//
// Module ID : TB-009
// Module    : tb_compute_tile_4pe
// Author    : Daniel Simpson
//
// Description:
// Clock-driven testbench for the 4-Processing Element AI Compute Tile.
//
//====================================================

`timescale 1ns/1ps

module tb_compute_tile_4pe;

    reg clk;
    reg rst;

    reg act_load;
    reg wgt_load;
    reg acc_clear;
    reg compute_en;

    reg signed [31:0] activations;
    reg signed [31:0] weights;

    wire signed [31:0] tile_result;
    wire done;

    compute_tile_4pe uut (
        .clk(clk),
        .rst(rst),
        .act_load(act_load),
        .wgt_load(wgt_load),
        .acc_clear(acc_clear),
        .compute_en(compute_en),
        .activations(activations),
        .weights(weights),
        .tile_result(tile_result),
        .done(done)
    );

    always #5 clk = ~clk;

    initial begin
        $dumpfile("compute_tile_4pe.vcd");
        $dumpvars(0, tb_compute_tile_4pe);

        clk = 0;
        rst = 0;
        act_load = 0;
        wgt_load = 0;
        acc_clear = 0;
        compute_en = 0;
        activations = 32'sd0;
        weights = 32'sd0;

        // Reset
        @(negedge clk);
        rst = 1;
        @(negedge clk);
        rst = 0;

        // Load Test 1: [1,2,3,4] dot [5,6,7,8] = 70
        @(negedge clk);
        activations = {8'sd4, 8'sd3, 8'sd2, 8'sd1};
        weights     = {8'sd8, 8'sd7, 8'sd6, 8'sd5};
        act_load = 1;
        wgt_load = 1;

        @(negedge clk);
        act_load = 0;
        wgt_load = 0;

        // Compute once
        @(negedge clk);
        compute_en = 1;

        @(negedge clk);
        compute_en = 0;

        // Load Test 2 activations only: [5,6,7,8] using same weights = 174
        @(negedge clk);
        activations = {8'sd8, 8'sd7, 8'sd6, 8'sd5};
        act_load = 1;

        @(negedge clk);
        act_load = 0;

        // Compute once: total should be 70 + 174 = 244
        @(negedge clk);
        compute_en = 1;

        @(negedge clk);
        compute_en = 0;

        // Hold for two cycles
        @(negedge clk);
        @(negedge clk);

        // Clear accumulator
        @(negedge clk);
        acc_clear = 1;

        @(negedge clk);
        acc_clear = 0;

        // Compute once after clear: should be 174
        @(negedge clk);
        compute_en = 1;

        @(negedge clk);
        compute_en = 0;

        @(negedge clk);
        $finish;
    end

endmodule

compute_tile_4pe.vcd
$date
	Sat Jul 04 18:45:29 2026
$end
$version
	Icarus Verilog
$end
$timescale
	1ps
$end
$scope module tb_compute_tile_4pe $end
$var wire 32 ! tile_result [31:0] $end
$var wire 1 " done $end
$var reg 1 # acc_clear $end
$var reg 1 $ act_load $end
$var reg 32 % activations [31:0] $end
$var reg 1 & clk $end
$var reg 1 ' compute_en $end
$var reg 1 ( rst $end
$var reg 32 ) weights [31:0] $end
$var reg 1 * wgt_load $end
$scope module uut $end
$var wire 1 # acc_clear $end
$var wire 1 $ act_load $end
$var wire 32 + activations [31:0] $end
$var wire 1 & clk $end
$var wire 1 ' compute_en $end
$var wire 1 ( rst $end
$var wire 32 , weights [31:0] $end
$var wire 1 * wgt_load $end
$var wire 8 - wgt3 [7:0] $end
$var wire 8 . wgt2 [7:0] $end
$var wire 8 / wgt1 [7:0] $end
$var wire 8 0 wgt0 [7:0] $end
$var wire 32 1 tile_result [31:0] $end
$var wire 8 2 act3 [7:0] $end
$var wire 8 3 act2 [7:0] $end
$var wire 8 4 act1 [7:0] $end
$var wire 8 5 act0 [7:0] $end
$var wire 32 6 acc3 [31:0] $end
$var wire 32 7 acc2 [31:0] $end
$var wire 32 8 acc1 [31:0] $end
$var wire 32 9 acc0 [31:0] $end
$var reg 1 " done $end
$scope module pe0 $end
$var wire 1 # acc_clear $end
$var wire 8 : act_in [7:0] $end
$var wire 1 $ act_load $end
$var wire 1 & clk $end
$var wire 1 ' compute_en $end
$var wire 1 ( rst $end
$var wire 8 ; wgt_in [7:0] $end
$var wire 1 * wgt_load $end
$var wire 32 < acc_out [31:0] $end
$var reg 8 = act_reg [7:0] $end
$var reg 8 > wgt_reg [7:0] $end
$scope module pe_mac $end
$var wire 8 ? a [7:0] $end
$var wire 8 @ b [7:0] $end
$var wire 1 # clear_acc $end
$var wire 1 & clk $end
$var wire 1 ' en $end
$var wire 1 ( rst $end
$var wire 32 A product_ext [31:0] $end
$var wire 16 B product [15:0] $end
$var parameter 32 C ACC_WIDTH $end
$var parameter 32 D DATA_WIDTH $end
$var parameter 64 E PRODUCT_WIDTH $end
$var reg 32 F acc [31:0] $end
$upscope $end
$upscope $end
$scope module pe1 $end
$var wire 1 # acc_clear $end
$var wire 8 G act_in [7:0] $end
$var wire 1 $ act_load $end
$var wire 1 & clk $end
$var wire 1 ' compute_en $end
$var wire 1 ( rst $end
$var wire 8 H wgt_in [7:0] $end
$var wire 1 * wgt_load $end
$var wire 32 I acc_out [31:0] $end
$var reg 8 J act_reg [7:0] $end
$var reg 8 K wgt_reg [7:0] $end
$scope module pe_mac $end
$var wire 8 L a [7:0] $end
$var wire 8 M b [7:0] $end
$var wire 1 # clear_acc $end
$var wire 1 & clk $end
$var wire 1 ' en $end
$var wire 1 ( rst $end
$var wire 32 N product_ext [31:0] $end
$var wire 16 O product [15:0] $end
$var parameter 32 P ACC_WIDTH $end
$var parameter 32 Q DATA_WIDTH $end
$var parameter 64 R PRODUCT_WIDTH $end
$var reg 32 S acc [31:0] $end
$upscope $end
$upscope $end
$scope module pe2 $end
$var wire 1 # acc_clear $end
$var wire 8 T act_in [7:0] $end
$var wire 1 $ act_load $end
$var wire 1 & clk $end
$var wire 1 ' compute_en $end
$var wire 1 ( rst $end
$var wire 8 U wgt_in [7:0] $end
$var wire 1 * wgt_load $end
$var wire 32 V acc_out [31:0] $end
$var reg 8 W act_reg [7:0] $end
$var reg 8 X wgt_reg [7:0] $end
$scope module pe_mac $end
$var wire 8 Y a [7:0] $end
$var wire 8 Z b [7:0] $end
$var wire 1 # clear_acc $end
$var wire 1 & clk $end
$var wire 1 ' en $end
$var wire 1 ( rst $end
$var wire 32 [ product_ext [31:0] $end
$var wire 16 \ product [15:0] $end
$var parameter 32 ] ACC_WIDTH $end
$var parameter 32 ^ DATA_WIDTH $end
$var parameter 64 _ PRODUCT_WIDTH $end
$var reg 32 ` acc [31:0] $end
$upscope $end
$upscope $end
$scope module pe3 $end
$var wire 1 # acc_clear $end
$var wire 8 a act_in [7:0] $end
$var wire 1 $ act_load $end
$var wire 1 & clk $end
$var wire 1 ' compute_en $end
$var wire 1 ( rst $end
$var wire 8 b wgt_in [7:0] $end
$var wire 1 * wgt_load $end
$var wire 32 c acc_out [31:0] $end
$var reg 8 d act_reg [7:0] $end
$var reg 8 e wgt_reg [7:0] $end
$scope module pe_mac $end
$var wire 8 f a [7:0] $end
$var wire 8 g b [7:0] $end
$var wire 1 # clear_acc $end
$var wire 1 & clk $end
$var wire 1 ' en $end
$var wire 1 ( rst $end
$var wire 32 h product_ext [31:0] $end
$var wire 16 i product [15:0] $end
$var parameter 32 j ACC_WIDTH $end
$var parameter 32 k DATA_WIDTH $end
$var parameter 64 l PRODUCT_WIDTH $end
$var reg 32 m acc [31:0] $end
$upscope $end
$upscope $end
$upscope $end
$upscope $end
$enddefinitions $end
$comment Show the parameter values. $end
$dumpall
b10000 l
b1000 k
b100000 j
b10000 _
b1000 ^
b100000 ]
b10000 R
b1000 Q
b100000 P
b10000 E
b1000 D
b100000 C
$end
#0
$dumpvars
bx m
bx i
bx h
bx g
bx f
bx e
bx d
bx c
b0 b
b0 a
bx `
bx \
bx [
bx Z
bx Y
bx X
bx W
bx V
b0 U
b0 T
bx S
bx O
bx N
bx M
bx L
bx K
bx J
bx I
b0 H
b0 G
bx F
bx B
bx A
bx @
bx ?
bx >
bx =
bx <
b0 ;
b0 :
bx 9
bx 8
bx 7
bx 6
b0 5
b0 4
b0 3
b0 2
bx 1
b0 0
b0 /
b0 .
b0 -
b0 ,
b0 +
0*
b0 )
0(
0'
0&
b0 %
0$
0#
x"
bx !
$end
#5000
0"
1&
#10000
1(
0&
#15000
b0 h
b0 i
b0 e
b0 g
b0 d
b0 f
b0 !
b0 1
b0 6
b0 c
b0 m
b0 [
b0 \
b0 X
b0 Z
b0 W
b0 Y
b0 7
b0 V
b0 `
b0 N
b0 O
b0 K
b0 M
b0 J
b0 L
b0 8
b0 I
b0 S
b0 A
b0 B
b0 >
b0 @
b0 =
b0 ?
b0 9
b0 <
b0 F
1&
#20000
0(
0&
#25000
1&
#30000
b101 0
b101 ;
b110 /
b110 H
b111 .
b111 U
b1000 -
b1000 b
b1 5
b1 :
b10 4
b10 G
b11 3
b11 T
b100 2
b100 a
1*
1$
b1000000001110000011000000101 )
b1000000001110000011000000101 ,
b100000000110000001000000001 %
b100000000110000001000000001 +
0&
#35000
b100000 h
b100000 i
b1000 e
b1000 g
b100 d
b100 f
b10101 [
b10101 \
b111 X
b111 Z
b11 W
b11 Y
b1100 N
b1100 O
b110 K
b110 M
b10 J
b10 L
b101 A
b101 B
b101 >
b101 @
b1 =
b1 ?
1&
#40000
0*
0$
0&
#45000
1&
#50000
1'
0&
#55000
1"
b100000 6
b100000 c
b100000 m
b10101 7
b10101 V
b10101 `
b1100 8
b1100 I
b1100 S
b1000110 !
b1000110 1
b101 9
b101 <
b101 F
1&
#60000
0'
0&
#65000
0"
1&
#70000
b101 5
b101 :
b110 4
b110 G
b111 3
b111 T
b1000 2
b1000 a
1$
b1000000001110000011000000101 %
b1000000001110000011000000101 +
0&
#75000
b1000000 h
b1000000 i
b1000 d
b1000 f
b110001 [
b110001 \
b111 W
b111 Y
b100100 N
b100100 O
b110 J
b110 L
b11001 A
b11001 B
b101 =
b101 ?
1&
#80000
0$
0&
#85000
1&
#90000
1'
0&
#95000
1"
b1100000 6
b1100000 c
b1100000 m
b1000110 7
b1000110 V
b1000110 `
b110000 8
b110000 I
b110000 S
b11110100 !
b11110100 1
b11110 9
b11110 <
b11110 F
1&
#100000
0'
0&
#105000
0"
1&
#110000
0&
#115000
1&
#120000
0&
#125000
1&
#130000
1#
0&
#135000
b0 6
b0 c
b0 m
b0 7
b0 V
b0 `
b0 8
b0 I
b0 S
b0 !
b0 1
b0 9
b0 <
b0 F
1&
#140000
0#
0&
#145000
1&
#150000
1'
0&
#155000
1"
b1000000 6
b1000000 c
b1000000 m
b110001 7
b110001 V
b110001 `
b100100 8
b100100 I
b100100 S
b10101110 !
b10101110 1
b11001 9
b11001 <
b11001 F
1&
#160000
0'
0&
#165000
0"
1&
