archive/compute_tile_dot4.v
//====================================================
// ForgeAI
//
// Module ID : FA-007
// Module    : compute_tile_dot4
// Author    : Daniel Simpson
//
// Description:
// INT8 signed 4-element dot product compute tile.
// Computes:
// result = a0*w0 + a1*w1 + a2*w2 + a3*w3
//
//====================================================

module compute_tile_dot4 (
    input  wire                     clk,
    input  wire                     rst,
    input  wire                     start,

    input  wire signed [7:0]        a0,
    input  wire signed [7:0]        a1,
    input  wire signed [7:0]        a2,
    input  wire signed [7:0]        a3,

    input  wire signed [7:0]        w0,
    input  wire signed [7:0]        w1,
    input  wire signed [7:0]        w2,
    input  wire signed [7:0]        w3,

    output reg  signed [31:0]       result,
    output reg                      done
);

    wire signed [15:0] p0;
    wire signed [15:0] p1;
    wire signed [15:0] p2;
    wire signed [15:0] p3;

    wire signed [31:0] sum;

    assign p0 = a0 * w0;
    assign p1 = a1 * w1;
    assign p2 = a2 * w2;
    assign p3 = a3 * w3;

    assign sum =
        {{16{p0[15]}}, p0} +
        {{16{p1[15]}}, p1} +
        {{16{p2[15]}}, p2} +
        {{16{p3[15]}}, p3};

    always @(posedge clk) begin
        if (rst) begin
            result <= 32'sd0;
            done   <= 1'b0;
        end else begin
            done <= 1'b0;

            if (start) begin
                result <= sum;
                done   <= 1'b1;
            end
        end
    end

endmodule

archive/tb_compute_tile_dot4.v
//====================================================
// ForgeAI
//
// Module ID : TB-007
// Module    : tb_compute_tile_dot4
// Author    : Daniel Simpson
//
// Description:
// Testbench for compute_tile_dot4.
//
//====================================================

`timescale 1ns/1ps

module tb_compute_tile_dot4;

    reg clk;
    reg rst;
    reg start;

    reg signed [7:0] a0, a1, a2, a3;
    reg signed [7:0] w0, w1, w2, w3;

    wire signed [31:0] result;
    wire done;

    compute_tile_dot4 uut (
        .clk(clk),
        .rst(rst),
        .start(start),

        .a0(a0), .a1(a1), .a2(a2), .a3(a3),
        .w0(w0), .w1(w1), .w2(w2), .w3(w3),

        .result(result),
        .done(done)
    );

    always #5 clk = ~clk;

    initial begin
        $dumpfile("compute_tile_dot4.vcd");
        $dumpvars(0, tb_compute_tile_dot4);

        clk = 0;
        rst = 0;
        start = 0;

        a0 = 0; a1 = 0; a2 = 0; a3 = 0;
        w0 = 0; w1 = 0; w2 = 0; w3 = 0;

        // Reset
        rst = 1;
        #10;
        rst = 0;

        // Test 1:
        // [1,2,3,4] dot [5,6,7,8]
        // 1*5 + 2*6 + 3*7 + 4*8 = 70
        a0 = 8'sd1; a1 = 8'sd2; a2 = 8'sd3; a3 = 8'sd4;
        w0 = 8'sd5; w1 = 8'sd6; w2 = 8'sd7; w3 = 8'sd8;

        start = 1;
        #10;
        start = 0;
        #10;

        // Test 2:
        // [-1,2,-3,4] dot [5,-6,7,-8]
        // -5 -12 -21 -32 = -70
        a0 = -8'sd1; a1 =  8'sd2; a2 = -8'sd3; a3 =  8'sd4;
        w0 =  8'sd5; w1 = -8'sd6; w2 =  8'sd7; w3 = -8'sd8;

        start = 1;
        #10;
        start = 0;
        #10;

        // Test 3:
        // [10,10,10,10] dot [1,1,1,1] = 40
        a0 = 8'sd10; a1 = 8'sd10; a2 = 8'sd10; a3 = 8'sd10;
        w0 = 8'sd1;  w1 = 8'sd1;  w2 = 8'sd1;  w3 = 8'sd1;

        start = 1;
        #10;
        start = 0;
        #10;

        $finish;
    end

endmodule

compute_tile_dot4.vcd
$date
	Sat Jul 04 16:14:27 2026
$end
$version
	Icarus Verilog
$end
$timescale
	1ps
$end
$scope module tb_compute_tile_dot4 $end
$var wire 32 ! result [31:0] $end
$var wire 1 " done $end
$var reg 8 # a0 [7:0] $end
$var reg 8 $ a1 [7:0] $end
$var reg 8 % a2 [7:0] $end
$var reg 8 & a3 [7:0] $end
$var reg 1 ' clk $end
$var reg 1 ( rst $end
$var reg 1 ) start $end
$var reg 8 * w0 [7:0] $end
$var reg 8 + w1 [7:0] $end
$var reg 8 , w2 [7:0] $end
$var reg 8 - w3 [7:0] $end
$scope module uut $end
$var wire 8 . a0 [7:0] $end
$var wire 8 / a1 [7:0] $end
$var wire 8 0 a2 [7:0] $end
$var wire 8 1 a3 [7:0] $end
$var wire 1 ' clk $end
$var wire 1 ( rst $end
$var wire 1 ) start $end
$var wire 8 2 w0 [7:0] $end
$var wire 8 3 w1 [7:0] $end
$var wire 8 4 w2 [7:0] $end
$var wire 8 5 w3 [7:0] $end
$var wire 32 6 sum [31:0] $end
$var wire 16 7 p3 [15:0] $end
$var wire 16 8 p2 [15:0] $end
$var wire 16 9 p1 [15:0] $end
$var wire 16 : p0 [15:0] $end
$var reg 1 " done $end
$var reg 32 ; result [31:0] $end
$upscope $end
$upscope $end
$enddefinitions $end
$comment Show the parameter values. $end
$dumpall
$end
#0
$dumpvars
bx ;
b0 :
b0 9
b0 8
b0 7
b0 6
b0 5
b0 4
b0 3
b0 2
b0 1
b0 0
b0 /
b0 .
b0 -
b0 ,
b0 +
b0 *
0)
1(
0'
b0 &
b0 %
b0 $
b0 #
x"
bx !
$end
#5000
0"
b0 !
b0 ;
1'
#10000
0'
1)
b100000 7
b1000 -
b1000 5
b10101 8
b111 ,
b111 4
b1100 9
b110 +
b110 3
b1000110 6
b101 :
b101 *
b101 2
b100 &
b100 1
b11 %
b11 0
b10 $
b10 /
b1 #
b1 .
0(
#15000
1"
b1000110 !
b1000110 ;
1'
#20000
0'
0)
#25000
0"
1'
#30000
0'
1)
b1111111111100000 7
b11111000 -
b11111000 5
b1111111111110100 9
b11111010 +
b11111010 3
b1111111111101011 8
b11111101 %
b11111101 0
b11111111111111111111111110111010 6
b1111111111111011 :
b11111111 #
b11111111 .
#35000
1"
b11111111111111111111111110111010 !
b11111111111111111111111110111010 ;
1'
#40000
0'
0)
#45000
0"
1'
#50000
0'
1)
b1 -
b1 5
b1 ,
b1 4
b1 +
b1 3
b1 *
b1 2
b1010 7
b1010 &
b1010 1
b1010 8
b1010 %
b1010 0
b1010 9
b1010 $
b1010 /
b101000 6
b1010 :
b1010 #
b1010 .
#55000
1"
b101000 !
b101000 ;
1'
#60000
0'
0)
#65000
0"
1'
