RTL/interface/forgeai_device_regs.v
//====================================================
// ForgeAI
//
// Module ID : FA-010
// Module    : forgeai_device_regs
// Author    : Daniel Simpson
//
// Description:
// Host-facing device register block for ForgeAI.
// Provides device identity, version, status, control,
// and result registers.
//
//====================================================

module forgeai_device_regs (
    input  wire        clk,
    input  wire        rst,

    input  wire        write_en,
    input  wire [7:0]  write_addr,
    input  wire [31:0] write_data,

    input  wire [7:0]  read_addr,
    output reg  [31:0] read_data,

    input  wire        busy,
    input  wire        done,
    input  wire [31:0] result_in,

    output reg         start,
    output reg         clear
);

    localparam DEVICE_ID_ADDR = 8'h00;
    localparam VERSION_ADDR   = 8'h04;
    localparam STATUS_ADDR    = 8'h08;
    localparam CONTROL_ADDR   = 8'h0C;
    localparam RESULT_ADDR    = 8'h10;

    localparam DEVICE_ID      = 32'hF0A10001;
    localparam VERSION        = 32'h00000001;

    always @(posedge clk) begin
        if (rst) begin
            start <= 1'b0;
            clear <= 1'b0;
        end else begin
            start <= 1'b0;
            clear <= 1'b0;

            if (write_en && write_addr == CONTROL_ADDR) begin
                start <= write_data[0];
                clear <= write_data[1];
            end
        end
    end

    always @(*) begin
        case (read_addr)
            DEVICE_ID_ADDR: read_data = DEVICE_ID;
            VERSION_ADDR:   read_data = VERSION;
            STATUS_ADDR:    read_data = {30'd0, done, busy};
            CONTROL_ADDR:   read_data = 32'd0;
            RESULT_ADDR:    read_data = result_in;
            default:        read_data = 32'hDEADBEEF;
        endcase
    end

endmodule

tb/tb_forgeai_device_regs.v
//====================================================
// ForgeAI
//
// Module ID : TB-010
// Module    : tb_forgeai_device_regs
// Author    : Daniel Simpson
//
// Description:
// Testbench for ForgeAI host-facing device registers.
//
//====================================================

`timescale 1ns/1ps

module tb_forgeai_device_regs;

    reg clk;
    reg rst;

    reg        write_en;
    reg [7:0]  write_addr;
    reg [31:0] write_data;

    reg  [7:0]  read_addr;
    wire [31:0] read_data;

    reg        busy;
    reg        done;
    reg [31:0] result_in;

    wire start;
    wire clear;

    forgeai_device_regs uut (
        .clk(clk),
        .rst(rst),

        .write_en(write_en),
        .write_addr(write_addr),
        .write_data(write_data),

        .read_addr(read_addr),
        .read_data(read_data),

        .busy(busy),
        .done(done),
        .result_in(result_in),

        .start(start),
        .clear(clear)
    );

    always #5 clk = ~clk;

    initial begin
        $dumpfile("forgeai_device_regs.vcd");
        $dumpvars(0, tb_forgeai_device_regs);

        clk = 0;
        rst = 0;
        write_en = 0;
        write_addr = 8'h00;
        write_data = 32'h00000000;
        read_addr = 8'h00;
        busy = 0;
        done = 0;
        result_in = 32'h00000000;

        // Reset
        @(negedge clk);
        rst = 1;
        @(negedge clk);
        rst = 0;

        // Read DEVICE_ID
        @(negedge clk);
        read_addr = 8'h00;

        // Read VERSION
        @(negedge clk);
        read_addr = 8'h04;

        // Read STATUS: busy=1, done=0
        @(negedge clk);
        busy = 1;
        done = 0;
        read_addr = 8'h08;

        // Read STATUS: busy=0, done=1
        @(negedge clk);
        busy = 0;
        done = 1;
        read_addr = 8'h08;

        // Read RESULT
        @(negedge clk);
        result_in = 32'h000000AE;
        read_addr = 8'h10;

        // Write CONTROL start bit
        @(negedge clk);
        write_addr = 8'h0C;
        write_data = 32'h00000001;
        write_en = 1;

        @(negedge clk);
        write_en = 0;
        write_data = 32'h00000000;

        // Write CONTROL clear bit
        @(negedge clk);
        write_addr = 8'h0C;
        write_data = 32'h00000002;
        write_en = 1;

        @(negedge clk);
        write_en = 0;

        @(negedge clk);
        $finish;
    end

endmodule

forgeai_device_regs.vcd
$date
	Sat Jul 04 21:55:27 2026
$end
$version
	Icarus Verilog
$end
$timescale
	1ps
$end
$scope module tb_forgeai_device_regs $end
$var wire 1 ! start $end
$var wire 32 " read_data [31:0] $end
$var wire 1 # clear $end
$var reg 1 $ busy $end
$var reg 1 % clk $end
$var reg 1 & done $end
$var reg 8 ' read_addr [7:0] $end
$var reg 32 ( result_in [31:0] $end
$var reg 1 ) rst $end
$var reg 8 * write_addr [7:0] $end
$var reg 32 + write_data [31:0] $end
$var reg 1 , write_en $end
$scope module uut $end
$var wire 1 $ busy $end
$var wire 1 % clk $end
$var wire 1 & done $end
$var wire 8 - read_addr [7:0] $end
$var wire 32 . result_in [31:0] $end
$var wire 1 ) rst $end
$var wire 8 / write_addr [7:0] $end
$var wire 32 0 write_data [31:0] $end
$var wire 1 , write_en $end
$var parameter 8 1 CONTROL_ADDR $end
$var parameter 32 2 DEVICE_ID $end
$var parameter 8 3 DEVICE_ID_ADDR $end
$var parameter 8 4 RESULT_ADDR $end
$var parameter 8 5 STATUS_ADDR $end
$var parameter 32 6 VERSION $end
$var parameter 8 7 VERSION_ADDR $end
$var reg 1 # clear $end
$var reg 32 8 read_data [31:0] $end
$var reg 1 ! start $end
$upscope $end
$upscope $end
$enddefinitions $end
$comment Show the parameter values. $end
$dumpall
b100 7
b1 6
b1000 5
b10000 4
b0 3
b11110000101000010000000000000001 2
b1100 1
$end
#0
$dumpvars
b11110000101000010000000000000001 8
b0 0
b0 /
b0 .
b0 -
0,
b0 +
b0 *
0)
b0 (
b0 '
0&
0%
0$
x#
b11110000101000010000000000000001 "
x!
$end
#5000
0#
0!
1%
#10000
1)
0%
#15000
1%
#20000
0)
0%
#25000
1%
#30000
0%
#35000
1%
#40000
b1 "
b1 8
b100 '
b100 -
0%
#45000
1%
#50000
b1000 '
b1000 -
1$
0%
#55000
1%
#60000
b10 "
b10 8
1&
0$
0%
#65000
1%
#70000
b10101110 "
b10101110 8
b10000 '
b10000 -
b10101110 (
b10101110 .
0%
#75000
1%
#80000
1,
b1 +
b1 0
b1100 *
b1100 /
0%
#85000
1!
1%
#90000
b0 +
b0 0
0,
0%
#95000
0!
1%
#100000
1,
b10 +
b10 0
0%
#105000
1#
1%
#110000
0,
0%
#115000
0#
1%
