archive/mac_int8.v
//====================================================
// ForgeAI
//
// Module ID : FA-005
// Module    : mac_int8
// Author    : Daniel Simpson
//
// Description:
// Signed INT8 multiply-accumulate unit.
// Performs: acc <= acc + (a * b)
//
// Standards:
// - Positive-edge clock
// - Active-high synchronous reset
// - Active-high enable
// - Signed INT8 arithmetic
// - Signed INT32 accumulator
//
//====================================================

module mac_int8 (
    input  wire               clk,
    input  wire               rst,
    input  wire               en,
    input  wire signed [7:0]  a,
    input  wire signed [7:0]  b,
    output reg  signed [31:0] acc
);

    wire signed [15:0] product;

    assign product = a * b;

    always @(posedge clk) begin
        if (rst) begin
            acc <= 32'sd0;
        end else if (en) begin
            acc <= acc + product;
        end
    end

endmodule

archive/tb_mac_int8.v
//====================================================
// ForgeAI
//
// Module ID : TB-005
// Module    : tb_mac_int8
// Author    : Daniel Simpson
//
// Description:
// Testbench for signed INT8 MAC unit.
//
//====================================================

`timescale 1ns/1ps

module tb_mac_int8;

    reg clk;
    reg rst;
    reg en;

    reg  signed [7:0]  a;
    reg  signed [7:0]  b;
    wire signed [31:0] acc;

    mac_int8 uut (
        .clk(clk),
        .rst(rst),
        .en(en),
        .a(a),
        .b(b),
        .acc(acc)
    );

    // 10 ns period = 100 MHz
    always #5 clk = ~clk;

    initial begin
        $dumpfile("mac_int8.vcd");
        $dumpvars(0, tb_mac_int8);

        clk = 0;
        rst = 0;
        en  = 0;
        a   = 8'sd0;
        b   = 8'sd0;

        // Reset accumulator
        rst = 1;
        #10;
        rst = 0;

        // acc = 0 + (5 * 7) = 35
        en = 1;
        a  = 8'sd5;
        b  = 8'sd7;
        #10;

        // acc = 35 + (-3 * 10) = 5
        a = -8'sd3;
        b =  8'sd10;
        #10;

        // acc = 5 + (-4 * -6) = 29
        a = -8'sd4;
        b = -8'sd6;
        #10;

        // Disable enable; acc should hold 29
        en = 0;
        a  = 8'sd100;
        b  = 8'sd100;
        #20;

        // Re-enable; acc = 29 + (2 * -8) = 13
        en = 1;
        a  =  8'sd2;
        b  = -8'sd8;
        #10;

        // Reset again; acc = 0
        rst = 1;
        #10;
        rst = 0;
        en  = 0;

        #10;

        $finish;
    end

endmodule

mac_int8.vcd
$date
	Sat Jul 04 13:56:30 2026
$end
$version
	Icarus Verilog
$end
$timescale
	1ps
$end
$scope module tb_mac_int8 $end
$var wire 32 ! acc [31:0] $end
$var reg 8 " a [7:0] $end
$var reg 8 # b [7:0] $end
$var reg 1 $ clk $end
$var reg 1 % en $end
$var reg 1 & rst $end
$scope module uut $end
$var wire 8 ' a [7:0] $end
$var wire 8 ( b [7:0] $end
$var wire 1 $ clk $end
$var wire 1 % en $end
$var wire 1 & rst $end
$var wire 16 ) product [15:0] $end
$var reg 32 * acc [31:0] $end
$upscope $end
$upscope $end
$enddefinitions $end
$comment Show the parameter values. $end
$dumpall
$end
#0
$dumpvars
bx *
b0 )
b0 (
b0 '
1&
0%
0$
b0 #
b0 "
bx !
$end
#5000
b0 !
b0 *
1$
#10000
0$
b100011 )
b111 #
b111 (
b101 "
b101 '
1%
0&
#15000
b100011 !
b100011 *
1$
#20000
0$
b1010 #
b1010 (
b1111111111100010 )
b11111101 "
b11111101 '
#25000
b101 !
b101 *
1$
#30000
0$
b11111010 #
b11111010 (
b11000 )
b11111100 "
b11111100 '
#35000
b11101 !
b11101 *
1$
#40000
0$
b1100100 #
b1100100 (
b10011100010000 )
b1100100 "
b1100100 '
0%
#45000
1$
#50000
0$
#55000
1$
#60000
0$
b11111000 #
b11111000 (
b1111111111110000 )
b10 "
b10 '
1%
#65000
b1101 !
b1101 *
1$
#70000
0$
1&
#75000
b0 !
b0 *
1$
#80000
0$
0%
0&
