RTL/compute/macN.v
//====================================================
// ForgeAI
//
// Module ID : FA-006
// Module    : macN
// Author    : Daniel Simpson
//
// Description:
// Parameterized signed multiply-accumulate unit.
// Performs: acc <= acc + (a * b)
//
// Standards:
// - Positive-edge clock
// - Active-high synchronous reset
// - Active-high enable
// - Active-high accumulator clear
// - Signed arithmetic
//
//====================================================

module macN #(
    parameter DATA_WIDTH = 8,
    parameter ACC_WIDTH  = 32
)(
    input  wire                         clk,
    input  wire                         rst,
    input  wire                         clear_acc,
    input  wire                         en,
    input  wire signed [DATA_WIDTH-1:0] a,
    input  wire signed [DATA_WIDTH-1:0] b,
    output reg  signed [ACC_WIDTH-1:0]  acc
);

    localparam PRODUCT_WIDTH = DATA_WIDTH * 2;

    wire signed [PRODUCT_WIDTH-1:0] product;
    wire signed [ACC_WIDTH-1:0]     product_ext;

    assign product     = a * b;
    assign product_ext = {{(ACC_WIDTH-PRODUCT_WIDTH){product[PRODUCT_WIDTH-1]}}, product};

    always @(posedge clk) begin
        if (rst) begin
            acc <= {ACC_WIDTH{1'b0}};
        end else if (clear_acc) begin
            acc <= {ACC_WIDTH{1'b0}};
        end else if (en) begin
            acc <= acc + product_ext;
        end
    end

endmodule

tb/tb_macN.v
//====================================================
// ForgeAI
//
// Module ID : TB-006
// Module    : tb_macN
// Author    : Daniel Simpson
//
// Description:
// Testbench for parameterized signed MAC with clear_acc.
//
//====================================================

`timescale 1ns/1ps

module tb_macN;

    reg clk;
    reg rst;
    reg clear_acc;
    reg en;

    reg  signed [7:0]  a8;
    reg  signed [7:0]  b8;
    wire signed [31:0] acc8;

    macN #(
        .DATA_WIDTH(8),
        .ACC_WIDTH(32)
    ) mac8_uut (
        .clk(clk),
        .rst(rst),
        .clear_acc(clear_acc),
        .en(en),
        .a(a8),
        .b(b8),
        .acc(acc8)
    );

    always #5 clk = ~clk;

    initial begin
        $dumpfile("macN.vcd");
        $dumpvars(0, tb_macN);

        clk = 0;
        rst = 0;
        clear_acc = 0;
        en  = 0;
        a8  = 8'sd0;
        b8  = 8'sd0;

        // Reset
        rst = 1;
        #10;
        rst = 0;

        // acc = 0 + 5*7 = 35
        en = 1;
        a8 = 8'sd5;
        b8 = 8'sd7;
        #10;

        // acc = 35 + -3*10 = 5
        a8 = -8'sd3;
        b8 =  8'sd10;
        #10;

        // Clear accumulator without reset
        clear_acc = 1;
        #10;
        clear_acc = 0;

        // acc = 0 + -4*-6 = 24
        a8 = -8'sd4;
        b8 = -8'sd6;
        #10;

        // Hold test
        en = 0;
        a8 = 8'sd100;
        b8 = 8'sd100;
        #20;

        // Re-enable: acc = 24 + 2*-8 = 8
        en = 1;
        a8 =  8'sd2;
        b8 = -8'sd8;
        #10;

        $finish;
    end

endmodule

macN.vcd
$date
	Sat Jul 04 14:20:39 2026
$end
$version
	Icarus Verilog
$end
$timescale
	1ps
$end
$scope module tb_macN $end
$var wire 32 ! acc8 [31:0] $end
$var reg 8 " a8 [7:0] $end
$var reg 8 # b8 [7:0] $end
$var reg 1 $ clear_acc $end
$var reg 1 % clk $end
$var reg 1 & en $end
$var reg 1 ' rst $end
$scope module mac8_uut $end
$var wire 8 ( a [7:0] $end
$var wire 8 ) b [7:0] $end
$var wire 1 $ clear_acc $end
$var wire 1 % clk $end
$var wire 1 & en $end
$var wire 1 ' rst $end
$var wire 32 * product_ext [31:0] $end
$var wire 16 + product [15:0] $end
$var parameter 32 , ACC_WIDTH $end
$var parameter 32 - DATA_WIDTH $end
$var parameter 64 . PRODUCT_WIDTH $end
$var reg 32 / acc [31:0] $end
$upscope $end
$upscope $end
$enddefinitions $end
$comment Show the parameter values. $end
$dumpall
b10000 .
b1000 -
b100000 ,
$end
#0
$dumpvars
bx /
b0 +
b0 *
b0 )
b0 (
1'
0&
0%
0$
b0 #
b0 "
bx !
$end
#5000
b0 !
b0 /
1%
#10000
0%
b100011 *
b100011 +
b111 #
b111 )
b101 "
b101 (
1&
0'
#15000
b100011 !
b100011 /
1%
#20000
0%
b1010 #
b1010 )
b11111111111111111111111111100010 *
b1111111111100010 +
b11111101 "
b11111101 (
#25000
b101 !
b101 /
1%
#30000
0%
1$
#35000
b0 !
b0 /
1%
#40000
0%
b11111010 #
b11111010 )
b11000 *
b11000 +
b11111100 "
b11111100 (
0$
#45000
b11000 !
b11000 /
1%
#50000
0%
b1100100 #
b1100100 )
b10011100010000 *
b10011100010000 +
b1100100 "
b1100100 (
0&
#55000
1%
#60000
0%
#65000
1%
#70000
0%
b11111000 #
b11111000 )
b11111111111111111111111111110000 *
b1111111111110000 +
b10 "
b10 (
1&
#75000
b1000 !
b1000 /
1%
