RTL/compute/macN.v
//====================================================
// ForgeAI
//
// Module ID : FA-006
// Module    : macN
// Author    : Daniel Simpson
//
// Description:
// Parameterized signed multiply-accumulate unit.
// Performs: acc <= acc + (a * b)
//
// Standards:
// - Positive-edge clock
// - Active-high synchronous reset
// - Active-high enable
// - Active-high accumulator clear
// - Signed arithmetic
//
//====================================================

module macN #(
    parameter DATA_WIDTH = 8,
    parameter ACC_WIDTH  = 32
)(
    input  wire                         clk,
    input  wire                         rst,
    input  wire                         clear_acc,
    input  wire                         en,
    input  wire signed [DATA_WIDTH-1:0] a,
    input  wire signed [DATA_WIDTH-1:0] b,
    output reg  signed [ACC_WIDTH-1:0]  acc
);

    localparam PRODUCT_WIDTH = DATA_WIDTH * 2;

    wire signed [PRODUCT_WIDTH-1:0] product;
    wire signed [ACC_WIDTH-1:0]     product_ext;

    assign product     = a * b;
    assign product_ext = {{(ACC_WIDTH-PRODUCT_WIDTH){product[PRODUCT_WIDTH-1]}}, product};

    always @(posedge clk) begin
        if (rst) begin
            acc <= {ACC_WIDTH{1'b0}};
        end else if (clear_acc) begin
            acc <= {ACC_WIDTH{1'b0}};
        end else if (en) begin
            acc <= acc + product_ext;
        end
    end

endmodule

RTL/compute/processing_element.v
//====================================================
// ForgeAI
//
// Module ID : FA-008
// Module    : processing_element
// Author    : Daniel Simpson
//
// Description:
// AI Processing Element.
// Holds one signed INT8 activation, one signed INT8 weight,
// and feeds them into a signed MAC accumulator.
//
//====================================================

module processing_element (
    input  wire               clk,
    input  wire               rst,

    input  wire               act_load,
    input  wire               wgt_load,
    input  wire               acc_clear,
    input  wire               compute_en,

    input  wire signed [7:0]  act_in,
    input  wire signed [7:0]  wgt_in,

    output wire signed [31:0] acc_out
);

    reg signed [7:0] act_reg;
    reg signed [7:0] wgt_reg;

    always @(posedge clk) begin
        if (rst) begin
            act_reg <= 8'sd0;
            wgt_reg <= 8'sd0;
        end else begin
            if (act_load) begin
                act_reg <= act_in;
            end

            if (wgt_load) begin
                wgt_reg <= wgt_in;
            end
        end
    end

    macN #(
        .DATA_WIDTH(8),
        .ACC_WIDTH(32)
    ) pe_mac (
        .clk(clk),
        .rst(rst),
        .clear_acc(acc_clear),
        .en(compute_en),
        .a(act_reg),
        .b(wgt_reg),
        .acc(acc_out)
    );

endmodule

tb/tb_processing_element.v
//====================================================
// ForgeAI
//
// Module ID : TB-008
// Module    : tb_processing_element
// Author    : Daniel Simpson
//
// Description:
// Testbench for AI Processing Element.
//
//====================================================

`timescale 1ns/1ps

module tb_processing_element;

    reg clk;
    reg rst;

    reg act_load;
    reg wgt_load;
    reg acc_clear;
    reg compute_en;

    reg signed [7:0] act_in;
    reg signed [7:0] wgt_in;

    wire signed [31:0] acc_out;

    processing_element uut (
        .clk(clk),
        .rst(rst),
        .act_load(act_load),
        .wgt_load(wgt_load),
        .acc_clear(acc_clear),
        .compute_en(compute_en),
        .act_in(act_in),
        .wgt_in(wgt_in),
        .acc_out(acc_out)
    );

    always #5 clk = ~clk;

    initial begin
        $dumpfile("processing_element.vcd");
        $dumpvars(0, tb_processing_element);

        clk = 0;
        rst = 0;
        act_load = 0;
        wgt_load = 0;
        acc_clear = 0;
        compute_en = 0;
        act_in = 8'sd0;
        wgt_in = 8'sd0;

        // Reset
        rst = 1;
        #10;
        rst = 0;

        // Load activation = 5, weight = 7
        act_in = 8'sd5;
        wgt_in = 8'sd7;
        act_load = 1;
        wgt_load = 1;
        #10;
        act_load = 0;
        wgt_load = 0;

        // Compute: acc = 35
        compute_en = 1;
        #10;

        // Load new activation only: activation = -3, weight stays 7
        act_in = -8'sd3;
        act_load = 1;
        #10;
        act_load = 0;

        // Compute: acc = 35 + (-3 * 7) = 14
        #10;

        // Load new weight only: weight = -2, activation stays -3
        wgt_in = -8'sd2;
        wgt_load = 1;
        #10;
        wgt_load = 0;

        // Compute: acc = 14 + (-3 * -2) = 20
        #10;

        // Hold test
        compute_en = 0;
        act_in = 8'sd100;
        wgt_in = 8'sd100;
        #20;

        // Clear accumulator
        acc_clear = 1;
        #10;
        acc_clear = 0;

        // Compute again with stored activation=-3 and weight=-2
        compute_en = 1;
        #10;

        $finish;
    end

endmodule

processing_element.vcd
$date
	Sat Jul 04 17:16:49 2026
$end
$version
	Icarus Verilog
$end
$timescale
	1ps
$end
$scope module tb_processing_element $end
$var wire 32 ! acc_out [31:0] $end
$var reg 1 " acc_clear $end
$var reg 8 # act_in [7:0] $end
$var reg 1 $ act_load $end
$var reg 1 % clk $end
$var reg 1 & compute_en $end
$var reg 1 ' rst $end
$var reg 8 ( wgt_in [7:0] $end
$var reg 1 ) wgt_load $end
$scope module uut $end
$var wire 1 " acc_clear $end
$var wire 8 * act_in [7:0] $end
$var wire 1 $ act_load $end
$var wire 1 % clk $end
$var wire 1 & compute_en $end
$var wire 1 ' rst $end
$var wire 8 + wgt_in [7:0] $end
$var wire 1 ) wgt_load $end
$var wire 32 , acc_out [31:0] $end
$var reg 8 - act_reg [7:0] $end
$var reg 8 . wgt_reg [7:0] $end
$scope module pe_mac $end
$var wire 8 / a [7:0] $end
$var wire 8 0 b [7:0] $end
$var wire 1 " clear_acc $end
$var wire 1 % clk $end
$var wire 1 & en $end
$var wire 1 ' rst $end
$var wire 32 1 product_ext [31:0] $end
$var wire 16 2 product [15:0] $end
$var parameter 32 3 ACC_WIDTH $end
$var parameter 32 4 DATA_WIDTH $end
$var parameter 64 5 PRODUCT_WIDTH $end
$var reg 32 6 acc [31:0] $end
$upscope $end
$upscope $end
$upscope $end
$enddefinitions $end
$comment Show the parameter values. $end
$dumpall
b10000 5
b1000 4
b100000 3
$end
#0
$dumpvars
bx 6
bx 2
bx 1
bx 0
bx /
bx .
bx -
bx ,
b0 +
b0 *
0)
b0 (
1'
0&
0%
0$
b0 #
0"
bx !
$end
#5000
b0 !
b0 ,
b0 6
b0 1
b0 2
b0 .
b0 0
b0 -
b0 /
1%
#10000
0%
1)
1$
b111 (
b111 +
b101 #
b101 *
0'
#15000
b100011 1
b100011 2
b111 .
b111 0
b101 -
b101 /
1%
#20000
0%
1&
0)
0$
#25000
b100011 !
b100011 ,
b100011 6
1%
#30000
0%
1$
b11111101 #
b11111101 *
#35000
b11111111111111111111111111101011 1
b1111111111101011 2
b11111101 -
b11111101 /
b1000110 !
b1000110 ,
b1000110 6
1%
#40000
0%
0$
#45000
b110001 !
b110001 ,
b110001 6
1%
#50000
0%
1)
b11111110 (
b11111110 +
#55000
b110 1
b110 2
b11111110 .
b11111110 0
b11100 !
b11100 ,
b11100 6
1%
#60000
0%
0)
#65000
b100010 !
b100010 ,
b100010 6
1%
#70000
0%
b1100100 (
b1100100 +
b1100100 #
b1100100 *
0&
#75000
1%
#80000
0%
#85000
1%
#90000
0%
1"
#95000
b0 !
b0 ,
b0 6
1%
#100000
0%
1&
0"
#105000
b110 !
b110 ,
b110 6
1%
