RTL/registerN.v
//====================================================
// ForgeAI
//
// Module: registerN
// Author: Daniel Simpson
//
// Description:
// Parameterized register with synchronous active-high
// reset and active-high enable.
//
//====================================================

module registerN #(
    parameter WIDTH = 8
)(
    input  wire             clk,
    input  wire             rst,
    input  wire             en,
    input  wire [WIDTH-1:0] d,
    output reg  [WIDTH-1:0] q
);

always @(posedge clk) begin
    if (rst) begin
        q <= {WIDTH{1'b0}};
    end else if (en) begin
        q <= d;
    end
end

endmodule

tb/tb_registerN.v
//====================================================
// ForgeAI
//
// Module: tb_registerN
// Author: Daniel Simpson
//
// Description:
// Testbench for parameterized registerN.
// Tests both 8-bit and 32-bit instances.
//
//====================================================

`timescale 1ns/1ps

module tb_registerN;

    reg clk;
    reg rst;
    reg en;

    reg  [7:0]  d8;
    wire [7:0]  q8;

    reg  [31:0] d32;
    wire [31:0] q32;

    registerN #(
        .WIDTH(8)
    ) reg8_uut (
        .clk(clk),
        .rst(rst),
        .en(en),
        .d(d8),
        .q(q8)
    );

    registerN #(
        .WIDTH(32)
    ) reg32_uut (
        .clk(clk),
        .rst(rst),
        .en(en),
        .d(d32),
        .q(q32)
    );

    always #5 clk = ~clk;

    initial begin
        $dumpfile("registerN.vcd");
        $dumpvars(0, tb_registerN);

        clk = 0;
        rst = 0;
        en  = 0;
        d8  = 8'h00;
        d32 = 32'h00000000;

        // Reset both registers
        rst = 1;
        #10;
        rst = 0;

        // Load both registers
        en  = 1;
        d8  = 8'hA5;
        d32 = 32'hDEADBEEF;
        #10;

        // Disable enable; both should hold
        en  = 0;
        d8  = 8'hFF;
        d32 = 32'hFFFFFFFF;
        #20;

        // Re-enable and load new values
        en  = 1;
        d8  = 8'h3C;
        d32 = 32'h12345678;
        #10;

        // Reset again
        rst = 1;
        #10;
        rst = 0;
        en  = 0;

        #10;

        $finish;
    end

endmodule

registerN.vcd
$date
	Fri Jul 03 22:59:39 2026
$end
$version
	Icarus Verilog
$end
$timescale
	1ps
$end
$scope module tb_registerN $end
$var wire 8 ! q8 [7:0] $end
$var wire 32 " q32 [31:0] $end
$var reg 1 # clk $end
$var reg 32 $ d32 [31:0] $end
$var reg 8 % d8 [7:0] $end
$var reg 1 & en $end
$var reg 1 ' rst $end
$scope module reg32_uut $end
$var wire 1 # clk $end
$var wire 32 ( d [31:0] $end
$var wire 1 & en $end
$var wire 1 ' rst $end
$var parameter 32 ) WIDTH $end
$var reg 32 * q [31:0] $end
$upscope $end
$scope module reg8_uut $end
$var wire 1 # clk $end
$var wire 8 + d [7:0] $end
$var wire 1 & en $end
$var wire 1 ' rst $end
$var parameter 32 , WIDTH $end
$var reg 8 - q [7:0] $end
$upscope $end
$upscope $end
$enddefinitions $end
$comment Show the parameter values. $end
$dumpall
b1000 ,
b100000 )
$end
#0
$dumpvars
bx -
b0 +
bx *
b0 (
1'
0&
b0 %
b0 $
0#
bx "
bx !
$end
#5000
b0 !
b0 -
b0 "
b0 *
1#
#10000
0#
b11011110101011011011111011101111 $
b11011110101011011011111011101111 (
b10100101 %
b10100101 +
1&
0'
#15000
b11011110101011011011111011101111 "
b11011110101011011011111011101111 *
b10100101 !
b10100101 -
1#
#20000
0#
b11111111111111111111111111111111 $
b11111111111111111111111111111111 (
b11111111 %
b11111111 +
0&
#25000
1#
#30000
0#
#35000
1#
#40000
0#
b10010001101000101011001111000 $
b10010001101000101011001111000 (
b111100 %
b111100 +
1&
#45000
b111100 !
b111100 -
b10010001101000101011001111000 "
b10010001101000101011001111000 *
1#
#50000
0#
1'
#55000
b0 "
b0 *
b0 !
b0 -
1#
#60000
0#
0&
0'
