RTL/register8.v
//====================================================
// ForgeAI
//
// Module: register8
// Author: Daniel Simpson
//
// Description:
// 8-bit register with synchronous active-high reset
// and active-high enable.
//
//====================================================

module register8 (
    input  wire       clk,
    input  wire       rst,
    input  wire       en,
    input  wire [7:0] d,
    output reg  [7:0] q
);

always @(posedge clk) begin
    if (rst) begin
        q <= 8'b00000000;
    end else if (en) begin
        q <= d;
    end
end

endmodule

tb/tb_register8.v
//====================================================
// ForgeAI
//
// Module: tb_register8
// Author: Daniel Simpson
//
// Description:
// Testbench for register8.
// Verifies reset, enable, load, and hold behavior.
//
//====================================================

`timescale 1ns/1ps

module tb_register8;

    reg        clk;
    reg        rst;
    reg        en;
    reg  [7:0] d;
    wire [7:0] q;

    register8 uut (
        .clk(clk),
        .rst(rst),
        .en(en),
        .d(d),
        .q(q)
    );

    // Clock generator: 10 ns period = 100 MHz
    always #5 clk = ~clk;

    initial begin
        $dumpfile("register8.vcd");
        $dumpvars(0, tb_register8);

        clk = 0;
        rst = 0;
        en  = 0;
        d   = 8'h00;

        // Reset the register
        rst = 1;
        #10;
        rst = 0;

        // Load A5
        d  = 8'hA5;
        en = 1;
        #10;

        // Disable enable and change input
        // q should HOLD A5
        en = 0;
        d  = 8'hFF;
        #20;

        // Re-enable and load 3C
        en = 1;
        d  = 8'h3C;
        #10;

        // Reset again
        rst = 1;
        #10;
        rst = 0;

        #10;

        $finish;
    end

endmodule

register8.vcd
$date
	Fri Jul 03 22:30:44 2026
$end
$version
	Icarus Verilog
$end
$timescale
	1ps
$end
$scope module tb_register8 $end
$var wire 8 ! q [7:0] $end
$var reg 1 " clk $end
$var reg 8 # d [7:0] $end
$var reg 1 $ en $end
$var reg 1 % rst $end
$scope module uut $end
$var wire 1 " clk $end
$var wire 8 & d [7:0] $end
$var wire 1 $ en $end
$var wire 1 % rst $end
$var reg 8 ' q [7:0] $end
$upscope $end
$upscope $end
$enddefinitions $end
$comment Show the parameter values. $end
$dumpall
$end
#0
$dumpvars
bx '
b0 &
1%
0$
b0 #
0"
bx !
$end
#5000
b0 !
b0 '
1"
#10000
0"
1$
b10100101 #
b10100101 &
0%
#15000
b10100101 !
b10100101 '
1"
#20000
0"
b11111111 #
b11111111 &
0$
#25000
1"
#30000
0"
#35000
1"
#40000
0"
b111100 #
b111100 &
1$
#45000
b111100 !
b111100 '
1"
#50000
0"
1%
#55000
b0 !
b0 '
1"
#60000
0"
0%
#65000
b111100 !
b111100 '
1"
