RTL/compute/streaming_processing_element.v
//====================================================
// ForgeAI
//
// Module ID : FA-015
// Module    : streaming_processing_element
// Author    : Daniel Simpson
//
// Description:
// Parameterized streaming processing element.
//
// On each enabled clock:
// - Forwards activation to the right
// - Forwards weight downward
// - Accumulates activation_in * weight_in
//
//====================================================

module streaming_processing_element #(
    parameter DATA_WIDTH = 8,
    parameter ACC_WIDTH  = 32
)(
    input  wire                           clk,
    input  wire                           rst,
    input  wire                           compute_en,
    input  wire                           clear_acc,

    input  wire signed [DATA_WIDTH-1:0]   activation_in,
    input  wire signed [DATA_WIDTH-1:0]   weight_in,

    output reg  signed [DATA_WIDTH-1:0]   activation_out,
    output reg  signed [DATA_WIDTH-1:0]   weight_out,
    output reg  signed [ACC_WIDTH-1:0]    acc_out
);

    localparam PRODUCT_WIDTH = DATA_WIDTH * 2;

    wire signed [PRODUCT_WIDTH-1:0] product;
    wire signed [ACC_WIDTH-1:0]     product_ext;

    assign product = activation_in * weight_in;

    assign product_ext = {
        {(ACC_WIDTH - PRODUCT_WIDTH){product[PRODUCT_WIDTH-1]}},
        product
    };

    always @(posedge clk) begin
        if (rst) begin
            activation_out <= {DATA_WIDTH{1'b0}};
            weight_out     <= {DATA_WIDTH{1'b0}};
            acc_out        <= {ACC_WIDTH{1'b0}};
        end else begin
            // Registered systolic forwarding
            activation_out <= activation_in;
            weight_out     <= weight_in;

            if (clear_acc) begin
                acc_out <= {ACC_WIDTH{1'b0}};
            end else if (compute_en) begin
                acc_out <= acc_out + product_ext;
            end
        end
    end

endmodule

tb/tb_streaming_processing_element.v
//====================================================
// ForgeAI
//
// Module ID : TB-015
// Module    : tb_streaming_processing_element
// Author    : Daniel Simpson
//
// Description:
// Testbench for the parameterized Streaming
// Processing Element.
//
// Verifies:
//   ✓ Operand forwarding
//   ✓ Signed multiply-accumulate
//   ✓ Accumulator clear
//   ✓ Compute enable
//
//====================================================

`timescale 1ns/1ps

module tb_streaming_processing_element;

    parameter DATA_WIDTH = 8;
    parameter ACC_WIDTH  = 32;

    reg clk;
    reg rst;

    reg compute_en;
    reg clear_acc;

    reg signed [DATA_WIDTH-1:0] activation_in;
    reg signed [DATA_WIDTH-1:0] weight_in;

    wire signed [DATA_WIDTH-1:0] activation_out;
    wire signed [DATA_WIDTH-1:0] weight_out;
    wire signed [ACC_WIDTH-1:0]  acc_out;

    //--------------------------------------------------
    // DUT
    //--------------------------------------------------

    streaming_processing_element #(
        .DATA_WIDTH(DATA_WIDTH),
        .ACC_WIDTH(ACC_WIDTH)
    ) uut (

        .clk(clk),
        .rst(rst),

        .compute_en(compute_en),
        .clear_acc(clear_acc),

        .activation_in(activation_in),
        .weight_in(weight_in),

        .activation_out(activation_out),
        .weight_out(weight_out),

        .acc_out(acc_out)

    );

    //--------------------------------------------------
    // Clock
    //--------------------------------------------------

    always #5 clk = ~clk;

    //--------------------------------------------------
    // Test
    //--------------------------------------------------

    initial begin

        $dumpfile("streaming_processing_element.vcd");
        $dumpvars(0, tb_streaming_processing_element);

        clk = 0;
        rst = 0;

        compute_en = 0;
        clear_acc  = 0;

        activation_in = 0;
        weight_in     = 0;

        //------------------------------------------
        // Reset
        //------------------------------------------

        @(negedge clk);
        rst = 1;

        @(negedge clk);
        rst = 0;

        //------------------------------------------
        // Clear accumulator
        //------------------------------------------

        @(negedge clk);
        clear_acc = 1;

        @(negedge clk);
        clear_acc = 0;

        //------------------------------------------
        // First operands
        // 7 * 6 = 42
        //------------------------------------------

        @(negedge clk);

        activation_in = 8'sd7;
        weight_in     = 8'sd6;

        compute_en = 1;

        @(negedge clk);

        //------------------------------------------
        // Second operands
        // -3 * 8 = -24
        //------------------------------------------

        activation_in = -8'sd3;
        weight_in     = 8'sd8;

        @(negedge clk);

        //------------------------------------------
        // Third operands
        // 5 * -2 = -10
        //------------------------------------------

        activation_in = 8'sd5;
        weight_in     = -8'sd2;

        @(negedge clk);

        //------------------------------------------
        // Stop computing
        //------------------------------------------

        compute_en = 0;

        repeat(4)
            @(negedge clk);

        $finish;

    end

endmodule

streaming_processing_element.vcd
$date
	Sun Jul 12 00:24:45 2026
$end
$version
	Icarus Verilog
$end
$timescale
	1ps
$end
$scope module tb_streaming_processing_element $end
$var wire 8 ! weight_out [7:0] $end
$var wire 8 " activation_out [7:0] $end
$var wire 32 # acc_out [31:0] $end
$var parameter 32 $ ACC_WIDTH $end
$var parameter 32 % DATA_WIDTH $end
$var reg 8 & activation_in [7:0] $end
$var reg 1 ' clear_acc $end
$var reg 1 ( clk $end
$var reg 1 ) compute_en $end
$var reg 1 * rst $end
$var reg 8 + weight_in [7:0] $end
$scope module uut $end
$var wire 8 , activation_in [7:0] $end
$var wire 1 ' clear_acc $end
$var wire 1 ( clk $end
$var wire 1 ) compute_en $end
$var wire 1 * rst $end
$var wire 8 - weight_in [7:0] $end
$var wire 32 . product_ext [31:0] $end
$var wire 16 / product [15:0] $end
$var parameter 32 0 ACC_WIDTH $end
$var parameter 32 1 DATA_WIDTH $end
$var parameter 64 2 PRODUCT_WIDTH $end
$var reg 32 3 acc_out [31:0] $end
$var reg 8 4 activation_out [7:0] $end
$var reg 8 5 weight_out [7:0] $end
$upscope $end
$upscope $end
$enddefinitions $end
$comment Show the parameter values. $end
$dumpall
b10000 2
b1000 1
b100000 0
b1000 %
b100000 $
$end
#0
$dumpvars
bx 5
bx 4
bx 3
b0 /
b0 .
b0 -
b0 ,
b0 +
0*
0)
0(
0'
b0 &
bx #
bx "
bx !
$end
#5000
b0 !
b0 5
b0 "
b0 4
1(
#10000
1*
0(
#15000
b0 #
b0 3
1(
#20000
0*
0(
#25000
1(
#30000
1'
0(
#35000
1(
#40000
0'
0(
#45000
1(
#50000
1)
b101010 .
b101010 /
b110 +
b110 -
b111 &
b111 ,
0(
#55000
b101010 #
b101010 3
b110 !
b110 5
b111 "
b111 4
1(
#60000
b1000 +
b1000 -
b11111111111111111111111111101000 .
b1111111111101000 /
b11111101 &
b11111101 ,
0(
#65000
b10010 #
b10010 3
b1000 !
b1000 5
b11111101 "
b11111101 4
1(
#70000
b11111110 +
b11111110 -
b11111111111111111111111111110110 .
b1111111111110110 /
b101 &
b101 ,
0(
#75000
b1000 #
b1000 3
b11111110 !
b11111110 5
b101 "
b101 4
1(
#80000
0)
0(
