RTL/compute/macN.v
//====================================================
// ForgeAI
//
// Module ID : FA-006
// Module    : macN
// Author    : Daniel Simpson
//
// Description:
// Parameterized signed multiply-accumulate unit.
// Performs: acc <= acc + (a * b)
//
// Standards:
// - Positive-edge clock
// - Active-high synchronous reset
// - Active-high enable
// - Active-high accumulator clear
// - Signed arithmetic
//
//====================================================

module macN #(
    parameter DATA_WIDTH = 8,
    parameter ACC_WIDTH  = 32
)(
    input  wire                         clk,
    input  wire                         rst,
    input  wire                         clear_acc,
    input  wire                         en,
    input  wire signed [DATA_WIDTH-1:0] a,
    input  wire signed [DATA_WIDTH-1:0] b,
    output reg  signed [ACC_WIDTH-1:0]  acc
);

    localparam PRODUCT_WIDTH = DATA_WIDTH * 2;

    wire signed [PRODUCT_WIDTH-1:0] product;
    wire signed [ACC_WIDTH-1:0]     product_ext;

    assign product     = a * b;
    assign product_ext = {{(ACC_WIDTH-PRODUCT_WIDTH){product[PRODUCT_WIDTH-1]}}, product};

    always @(posedge clk) begin
        if (rst) begin
            acc <= {ACC_WIDTH{1'b0}};
        end else if (clear_acc) begin
            acc <= {ACC_WIDTH{1'b0}};
        end else if (en) begin
            acc <= acc + product_ext;
        end
    end

endmodule

archive/systolic_processing_element.v
//====================================================
// ForgeAI
//
// Module ID : FA-013
// Module    : systolic_processing_element
// Author    : Daniel Simpson
//
// Description:
// Systolic Processing Element.
//
// Receives activation and weight operands,
// forwards them to neighboring PEs,
// and performs one signed INT8 MAC.
//
//====================================================

module systolic_processing_element (

    input  wire clk,
    input  wire rst,

    input  wire act_load,
    input  wire wgt_load,
    input  wire acc_clear,
    input  wire compute_en,

    input  wire signed [7:0] activation_in,
    input  wire signed [7:0] weight_in,

    output reg  signed [7:0] activation_out,
    output reg  signed [7:0] weight_out,

    output wire signed [31:0] acc_out

);

    //--------------------------------------------------
    // Internal Registers
    //--------------------------------------------------

    reg signed [7:0] activation_reg;
    reg signed [7:0] weight_reg;

    //--------------------------------------------------
    // Pipeline Registers
    //--------------------------------------------------

    always @(posedge clk) begin

        if (rst) begin

            activation_reg <= 0;
            weight_reg     <= 0;

            activation_out <= 0;
            weight_out     <= 0;

        end
        else begin

            if (act_load) begin

                activation_reg <= activation_in;
                activation_out <= activation_in;

            end

            if (wgt_load) begin

                weight_reg <= weight_in;
                weight_out <= weight_in;

            end

        end

    end

    //--------------------------------------------------
    // MAC Engine
    //--------------------------------------------------

        macN #(
        .DATA_WIDTH(8),
        .ACC_WIDTH(32)
    ) mac (

        .clk(clk),
        .rst(rst),
        .clear_acc(acc_clear),
        .en(compute_en),

        .a(activation_reg),
        .b(weight_reg),

        .acc(acc_out)

    );

endmodule

archive/tb_systolic_processing_element.v
//====================================================
// ForgeAI
//
// Module ID : TB-013
// Module    : tb_systolic_processing_element
// Author    : Daniel Simpson
//
// Description:
// Testbench for the systolic processing element.
//
// Verifies:
//   - Activation forwarding
//   - Weight forwarding
//   - MAC computation
//
//====================================================

`timescale 1ns/1ps

module tb_systolic_processing_element;

    reg clk;
    reg rst;

    reg act_load;
    reg wgt_load;
    reg acc_clear;
    reg compute_en;

    reg signed [7:0] activation_in;
    reg signed [7:0] weight_in;

    wire signed [7:0] activation_out;
    wire signed [7:0] weight_out;

    wire signed [31:0] acc_out;

    //--------------------------------------------------
    // DUT
    //--------------------------------------------------

    systolic_processing_element uut (

        .clk(clk),
        .rst(rst),

        .act_load(act_load),
        .wgt_load(wgt_load),
        .acc_clear(acc_clear),
        .compute_en(compute_en),

        .activation_in(activation_in),
        .weight_in(weight_in),

        .activation_out(activation_out),
        .weight_out(weight_out),

        .acc_out(acc_out)

    );

    //--------------------------------------------------
    // Clock
    //--------------------------------------------------

    always #5 clk = ~clk;

    //--------------------------------------------------
    // Test
    //--------------------------------------------------

    initial begin

        $dumpfile("systolic_processing_element.vcd");
        $dumpvars(0, tb_systolic_processing_element);

        clk = 0;
        rst = 0;

        act_load = 0;
        wgt_load = 0;
        acc_clear = 0;
        compute_en = 0;

        activation_in = 0;
        weight_in = 0;

        //------------------------------------------
        // Reset
        //------------------------------------------

        @(negedge clk);
        rst = 1;

        @(negedge clk);
        rst = 0;

        //------------------------------------------
        // Load operands
        //------------------------------------------

        @(negedge clk);

        activation_in = 8'sd7;
        weight_in     = 8'sd6;

        act_load = 1;
        wgt_load = 1;

        @(negedge clk);

        act_load = 0;
        wgt_load = 0;

        //------------------------------------------
        // Clear accumulator
        //------------------------------------------

        @(negedge clk);

        acc_clear = 1;

        @(negedge clk);

        acc_clear = 0;

        //------------------------------------------
        // Compute once
        //------------------------------------------

        @(negedge clk);

        compute_en = 1;

        @(negedge clk);

        compute_en = 0;

        //------------------------------------------
        // Compute again
        //------------------------------------------

        @(negedge clk);

        compute_en = 1;

        @(negedge clk);

        compute_en = 0;

        repeat (4)
            @(negedge clk);

        $finish;

    end

endmodule

systolic_processing_element.vcd
$date
	Mon Jul 06 20:49:08 2026
$end
$version
	Icarus Verilog
$end
$timescale
	1ps
$end
$scope module tb_systolic_processing_element $end
$var wire 8 ! weight_out [7:0] $end
$var wire 8 " activation_out [7:0] $end
$var wire 32 # acc_out [31:0] $end
$var reg 1 $ acc_clear $end
$var reg 1 % act_load $end
$var reg 8 & activation_in [7:0] $end
$var reg 1 ' clk $end
$var reg 1 ( compute_en $end
$var reg 1 ) rst $end
$var reg 8 * weight_in [7:0] $end
$var reg 1 + wgt_load $end
$scope module uut $end
$var wire 1 $ acc_clear $end
$var wire 1 % act_load $end
$var wire 8 , activation_in [7:0] $end
$var wire 1 ' clk $end
$var wire 1 ( compute_en $end
$var wire 1 ) rst $end
$var wire 8 - weight_in [7:0] $end
$var wire 1 + wgt_load $end
$var wire 32 . acc_out [31:0] $end
$var reg 8 / activation_out [7:0] $end
$var reg 8 0 activation_reg [7:0] $end
$var reg 8 1 weight_out [7:0] $end
$var reg 8 2 weight_reg [7:0] $end
$scope module mac $end
$var wire 8 3 a [7:0] $end
$var wire 8 4 b [7:0] $end
$var wire 1 $ clear_acc $end
$var wire 1 ' clk $end
$var wire 1 ( en $end
$var wire 1 ) rst $end
$var wire 32 5 product_ext [31:0] $end
$var wire 16 6 product [15:0] $end
$var parameter 32 7 ACC_WIDTH $end
$var parameter 32 8 DATA_WIDTH $end
$var parameter 64 9 PRODUCT_WIDTH $end
$var reg 32 : acc [31:0] $end
$upscope $end
$upscope $end
$upscope $end
$enddefinitions $end
$comment Show the parameter values. $end
$dumpall
b10000 9
b1000 8
b100000 7
$end
#0
$dumpvars
bx :
bx 6
bx 5
bx 4
bx 3
bx 2
bx 1
bx 0
bx /
bx .
b0 -
b0 ,
0+
b0 *
0)
0(
0'
b0 &
0%
0$
bx #
bx "
bx !
$end
#5000
1'
#10000
1)
0'
#15000
b0 !
b0 1
b0 "
b0 /
b0 5
b0 6
b0 2
b0 4
b0 0
b0 3
b0 #
b0 .
b0 :
1'
#20000
0)
0'
#25000
1'
#30000
1+
1%
b110 *
b110 -
b111 &
b111 ,
0'
#35000
b110 !
b110 1
b101010 5
b101010 6
b110 2
b110 4
b111 "
b111 /
b111 0
b111 3
1'
#40000
0+
0%
0'
#45000
1'
#50000
1$
0'
#55000
1'
#60000
0$
0'
#65000
1'
#70000
1(
0'
#75000
b101010 #
b101010 .
b101010 :
1'
#80000
0(
0'
#85000
1'
#90000
1(
0'
#95000
b1010100 #
b1010100 .
b1010100 :
1'
#100000
0(
0'
