RTL/interface/tile_controller_skeleton.v
//====================================================
// ForgeAI
//
// Module ID : FA-012A
// Module    : tile_controller_skeleton
// Author    : Daniel Simpson
//
// Description:
// Stage 1 tile controller skeleton.
// Verifies controller state sequencing only.
//
//====================================================

module tile_controller_skeleton (
    input  wire       clk,
    input  wire       rst,
    input  wire       start,

    output reg        busy,
    output reg        done,
    output reg [2:0]  state
);

    localparam IDLE       = 3'd0;
    localparam READ_ACT   = 3'd1;
    localparam READ_WGT   = 3'd2;
    localparam LOAD_TILE  = 3'd3;
    localparam COMPUTE    = 3'd4;
    localparam STORE_RES  = 3'd5;

    always @(posedge clk) begin
        if (rst) begin
            state <= IDLE;
            busy  <= 1'b0;
            done  <= 1'b0;
        end else begin
            done <= 1'b0;

            case (state)

                IDLE: begin
                    busy <= 1'b0;

                    if (start) begin
                        state <= READ_ACT;
                        busy  <= 1'b1;
                    end
                end

                READ_ACT: begin
                    state <= READ_WGT;
                end

                READ_WGT: begin
                    state <= LOAD_TILE;
                end

                LOAD_TILE: begin
                    state <= COMPUTE;
                end

                COMPUTE: begin
                    state <= STORE_RES;
                end

                STORE_RES: begin
                    state <= IDLE;
                    busy  <= 1'b0;
                    done  <= 1'b1;
                end

                default: begin
                    state <= IDLE;
                    busy  <= 1'b0;
                    done  <= 1'b0;
                end

            endcase
        end
    end

endmodule

archive/tb_tile_controller_skeleton.v
//====================================================
// ForgeAI
//
// Module ID : TB-012A
// Module    : tb_tile_controller_skeleton
// Author    : Daniel Simpson
//
// Description:
// Testbench for Tile Controller Skeleton.
//
//====================================================

`timescale 1ns/1ps

module tb_tile_controller_skeleton;

    reg clk;
    reg rst;
    reg start;

    wire busy;
    wire done;
    wire [2:0] state;

    tile_controller_skeleton uut (
        .clk(clk),
        .rst(rst),
        .start(start),
        .busy(busy),
        .done(done),
        .state(state)
    );

    // 100 MHz clock
    always #5 clk = ~clk;

    initial begin

        $dumpfile("tile_controller_skeleton.vcd");
        $dumpvars(0, tb_tile_controller_skeleton);

        clk   = 0;
        rst   = 0;
        start = 0;

        //---------------------------------------
        // Reset
        //---------------------------------------

        @(negedge clk);
        rst = 1;

        @(negedge clk);
        rst = 0;

        //---------------------------------------
        // Start one transaction
        //---------------------------------------

        @(negedge clk);
        start = 1;

        @(negedge clk);
        start = 0;

        //---------------------------------------
        // Wait long enough for controller
        //---------------------------------------

        repeat (8)
            @(negedge clk);

        //---------------------------------------
        // Start another transaction
        //---------------------------------------

        @(negedge clk);
        start = 1;

        @(negedge clk);
        start = 0;

        repeat (8)
            @(negedge clk);

        $finish;

    end

endmodule

tile_controller_skeleton.vcd
$date
	Sat Jul 04 23:41:43 2026
$end
$version
	Icarus Verilog
$end
$timescale
	1ps
$end
$scope module tb_tile_controller_skeleton $end
$var wire 3 ! state [2:0] $end
$var wire 1 " done $end
$var wire 1 # busy $end
$var reg 1 $ clk $end
$var reg 1 % rst $end
$var reg 1 & start $end
$scope module uut $end
$var wire 1 $ clk $end
$var wire 1 % rst $end
$var wire 1 & start $end
$var parameter 3 ' COMPUTE $end
$var parameter 3 ( IDLE $end
$var parameter 3 ) LOAD_TILE $end
$var parameter 3 * READ_ACT $end
$var parameter 3 + READ_WGT $end
$var parameter 3 , STORE_RES $end
$var reg 1 # busy $end
$var reg 1 " done $end
$var reg 3 - state [2:0] $end
$upscope $end
$upscope $end
$enddefinitions $end
$comment Show the parameter values. $end
$dumpall
b101 ,
b10 +
b1 *
b11 )
b0 (
b100 '
$end
#0
$dumpvars
bx -
0&
0%
0$
x#
x"
bx !
$end
#5000
0#
b0 !
b0 -
0"
1$
#10000
1%
0$
#15000
1$
#20000
0%
0$
#25000
1$
#30000
1&
0$
#35000
1#
b1 !
b1 -
1$
#40000
0&
0$
#45000
b10 !
b10 -
1$
#50000
0$
#55000
b11 !
b11 -
1$
#60000
0$
#65000
b100 !
b100 -
1$
#70000
0$
#75000
b101 !
b101 -
1$
#80000
0$
#85000
1"
0#
b0 !
b0 -
1$
#90000
0$
#95000
0"
1$
#100000
0$
#105000
1$
#110000
0$
#115000
1$
#120000
0$
#125000
1$
#130000
1&
0$
#135000
1#
b1 !
b1 -
1$
#140000
0&
0$
#145000
b10 !
b10 -
1$
#150000
0$
#155000
b11 !
b11 -
1$
#160000
0$
#165000
b100 !
b100 -
1$
#170000
0$
#175000
b101 !
b101 -
1$
#180000
0$
#185000
1"
0#
b0 !
b0 -
1$
#190000
0$
#195000
0"
1$
